[
    {
        "annee": 2013,
        "marque": "Ducati",
        "modele": "Diavel Dark",
	"CC":1198.4,
        "valInit": 19000
    },
    {
        "annee": 2013,
        "marque": "Ducati",
        "modele": "Hypermotard SP",
	"CC":821.1,
        "valInit": 16000
    },
    {
        "annee": 2013,
        "marque": "Ducati",
        "modele": "Monster 1100 Evo",
	"CC":1078,
        "valInit": 13500
    },
    {
        "annee": 2013,
        "marque": "Ducati",
        "modele": "Streetfighter 848",
	"CC":849,
        "valInit": 14300
    },
    {
        "annee": 2013,
        "marque": "Ducati",
        "modele": "Superbike 1199 Panigale R",
	"CC":1198,
        "valInit": 32000
    }    
]
